purecpp_websearch/__init__.py
purecpp_websearch/websearch/__init__.py
purecpp_websearch/websearch/__main__.py
purecpp_websearch/websearch/exceptions.py
purecpp_websearch/websearch/http.py
purecpp_websearch/websearch/mimes.py
purecpp_websearch/websearch/output.py
purecpp_websearch/websearch/pipeline.py
purecpp_websearch/websearch/router.py
purecpp_websearch/websearch/schemas.py
purecpp_websearch/websearch/settings.py
purecpp_websearch/websearch/utils.py
purecpp_websearch/websearch/cleaners/__init__.py
purecpp_websearch/websearch/cleaners/base.py
purecpp_websearch/websearch/cleaners/readability.py
purecpp_websearch/websearch/cleaners/simple.py
purecpp_websearch/websearch/fetchers/__init__.py
purecpp_websearch/websearch/fetchers/http_fetcher.py
purecpp_websearch/websearch/providers/__init__.py
purecpp_websearch/websearch/providers/base.py
purecpp_websearch/websearch/providers/brave.py
purecpp_websearch-1.0.0.dist-info/licenses/LICENSE
purecpp_websearch-1.0.0.dist-info/METADATA
purecpp_websearch-1.0.0.dist-info/WHEEL
purecpp_websearch-1.0.0.dist-info/top_level.txt
purecpp_websearch-1.0.0.dist-info/RECORD
