Metadata-Version: 2.4
Name: purecpp-websearch
Version: 1.0.0
Summary: PureCPP WebSearch integration
Author-email: pureai <contato@pureai.com.br>
Maintainer-email: pureai <contato@pureai.com.br>
License-Expression: MIT
Requires-Python: >=3.9
License-File: LICENSE
Requires-Dist: httpx>=0.27.0
Requires-Dist: asyncio>=3.4.3
Dynamic: license-file
